MANIFEST.in
README.rst
setup.py
collective/__init__.py
collective.portlet.colorcollection.egg-info/PKG-INFO
collective.portlet.colorcollection.egg-info/SOURCES.txt
collective.portlet.colorcollection.egg-info/dependency_links.txt
collective.portlet.colorcollection.egg-info/entry_points.txt
collective.portlet.colorcollection.egg-info/namespace_packages.txt
collective.portlet.colorcollection.egg-info/not-zip-safe
collective.portlet.colorcollection.egg-info/requires.txt
collective.portlet.colorcollection.egg-info/top_level.txt
collective/portlet/__init__.py
collective/portlet/colorcollection/__init__.py
collective/portlet/colorcollection/colorcollection.pt
collective/portlet/colorcollection/colorcollection.py
collective/portlet/colorcollection/configure.zcml
collective/portlet/colorcollection/interfaces.py
collective/portlet/colorcollection/setuphandlers.py
collective/portlet/colorcollection/profiles/default/browserlayer.xml
collective/portlet/colorcollection/profiles/default/catalog.xml
collective/portlet/colorcollection/profiles/default/collective.portlet.colorcollection_various.txt
collective/portlet/colorcollection/profiles/default/metadata.xml
collective/portlet/colorcollection/tests/__init__.py
collective/portlet/colorcollection/tests/base.py
collective/portlet/colorcollection/tests/test_portlet.py
docs/HISTORY.txt
docs/INSTALL.txt
docs/LICENSE.GPL
docs/LICENSE.txt